aws_lambda_client/__init__.py
aws_lambda_client/api_creator.py
aws_lambda_client/aws_auth.py
aws_lambda_client/client.py
aws_lambda_client/constants.py
aws_lambda_client/requester.py
aws_lambda_client/data/endpoints.json
aws_lambda_client/models/__init__.py
aws_lambda_client/models/arn.py
aws_lambda_client-0.1.0.dist-info/LICENSE
aws_lambda_client-0.1.0.dist-info/METADATA
aws_lambda_client-0.1.0.dist-info/WHEEL
aws_lambda_client-0.1.0.dist-info/top_level.txt
aws_lambda_client-0.1.0.dist-info/RECORD
